rastertoolkit/__init__.py
rastertoolkit/raster.py
rastertoolkit/shape.py
rastertoolkit/utils.py
rastertoolkit-0.4.5.dist-info/licenses/LICENSE
rastertoolkit-0.4.5.dist-info/METADATA
rastertoolkit-0.4.5.dist-info/WHEEL
rastertoolkit-0.4.5.dist-info/top_level.txt
rastertoolkit-0.4.5.dist-info/RECORD
