Metadata-Version: 2.4
Name: rastertoolkit
Version: 0.4.5
Summary: Raster and shape tools
Author-email: Kurt Frey <kurt.frey@gatesfoundation.org>, Dejan Lukacevic <dejan.lukacevic@gatesfoundation.org>, Katherine Rosenfeld <katherine.rosenfeld@gatesfoundation.org>
License-Expression: MIT
Project-URL: Documentation, https://institutefordiseasemodeling.github.io/RasterToolkit/
Project-URL: Repository, https://github.com/InstituteforDiseaseModeling/RasterToolkit
Project-URL: Issues, https://github.com/InstituteforDiseaseModeling/RasterToolkit/issues
Keywords: modeling,IDM
Classifier: Intended Audience :: Science/Research
Classifier: Programming Language :: Python :: 3
Classifier: Operating System :: OS Independent
Requires-Python: >=3.9
License-File: LICENSE
Requires-Dist: matplotlib~=3.9
Requires-Dist: pyshp~=3.0
Requires-Dist: pyproj~=3.6
Requires-Dist: scikit-learn~=1.6
Requires-Dist: shapely~=2.0
Provides-Extra: docs
Requires-Dist: mkdocs-material; extra == "docs"
Requires-Dist: mkdocs-include-markdown-plugin; extra == "docs"
Requires-Dist: mkdocstrings-python; extra == "docs"
Requires-Dist: mkdocs-autoapi; extra == "docs"
Requires-Dist: mkdocs-glightbox; extra == "docs"
Requires-Dist: mkdocs-jupyter; extra == "docs"
Provides-Extra: lint
Requires-Dist: flake8; extra == "lint"
Provides-Extra: test
Requires-Dist: pytest; extra == "test"
Requires-Dist: pytest-cov; extra == "test"
Dynamic: license-file
